<annotation>
	<folder>my-project-name</folder>
	<filename>Keria_03_1904_62.jpeg</filename>
	<path>/my-project-name/Keria_03_1904_62.jpeg</path>
	<source>
		<database>Unspecified</database>
	</source>
	<size>
		<width>260</width>
		<height>260</height>
		<depth>3</depth>
	</size>
	<object>
		<name>Basil</name>
		<pose>Unspecified</pose>
		<truncated>Unspecified</truncated>
		<difficult>Unspecified</difficult>
		<bndbox>
			<xmin>24</xmin>
			<ymin>187</ymin>
			<xmax>59</xmax>
			<ymax>230</ymax>
		</bndbox>
	</object>
</annotation>